fast_token_classifier/__init__.py
fast_token_classifier/config/__init__.py
fast_token_classifier/config/config.yaml
fast_token_classifier/config/core.py
fast_token_classifier/config/schema.py
fast_token_classifier/creds.py
fast_token_classifier/info_extraction/__init__.py
fast_token_classifier/info_extraction/predict.py
fast_token_classifier/info_extraction/train.py
fast_token_classifier/info_extraction/utils/__init__.py
fast_token_classifier/info_extraction/utils/data_loader.py
fast_token_classifier/info_extraction/utils/preprocessor.py
fast_token_classifier/info_extraction/utils/utilities.py
fast_token_classifier/logger.py
fast_token_classifier-0.2.8.dist-info/METADATA
fast_token_classifier-0.2.8.dist-info/WHEEL
fast_token_classifier-0.2.8.dist-info/RECORD
