Metadata-Version: 2.1
Name: fast-token-classifier
Version: 0.2.8
Summary: 
License: MIT
Author: Chinedu Ezeofor
Author-email: sneidue@email.com
Requires-Python: ==3.10.8
Classifier: License :: OSI Approved :: MIT License
Classifier: Programming Language :: Python :: 3
Requires-Dist: aiohttp (==3.7)
Requires-Dist: click (>=8.1.7,<9.0.0)
Requires-Dist: datasets (>=2.14.4,<3.0.0)
Requires-Dist: ensure (>=1.0.3,<2.0.0)
Requires-Dist: fastapi (>=0.90.0,<0.91.0)
Requires-Dist: fsspec (>=2023.9.2,<2024.0.0)
Requires-Dist: httpx (>=0.25.1,<0.26.0)
Requires-Dist: loguru (>=0.7.0,<0.8.0)
Requires-Dist: numpy (>=1.22.3,<2.0.0)
Requires-Dist: pre-commit (>=2.21.0,<3.0.0)
Requires-Dist: pydantic (<=1.10.13)
Requires-Dist: python-dotenv (>=1.0.0,<2.0.0)
Requires-Dist: rich (>=13.6.0,<14.0.0)
Requires-Dist: scikit-learn (>=1.2.1,<2.0.0)
Requires-Dist: scipy (==1.11.3)
Requires-Dist: seqeval (>=1.2.2,<2.0.0)
Requires-Dist: tensorflow (>=2.13,<3.0)
Requires-Dist: transformers (>=4.32.0,<5.0.0)
Requires-Dist: typeguard (>=2.13.3,<3.0.0)
Requires-Dist: uvicorn (>=0.24.0,<0.25.0)
